GRATIOSA/Chipseq.py
GRATIOSA/GO.py
GRATIOSA/Gene.py
GRATIOSA/Genome.py
GRATIOSA/HiC.py
GRATIOSA/TSS_TTS_TU.py
GRATIOSA/Transcriptome.py
GRATIOSA/__init__.py
GRATIOSA/globvar.py
GRATIOSA/plot_genome.py
GRATIOSA/plot_stat_analysis.py
GRATIOSA/stat_analysis.py
GRATIOSA/useful_functions_Chipseq.py
GRATIOSA/useful_functions_HiC.py
GRATIOSA/useful_functions_genome.py
GRATIOSA/useful_functions_transcriptome.py
GRATIOSA-1.0.2.dist-info/METADATA
GRATIOSA-1.0.2.dist-info/WHEEL
GRATIOSA-1.0.2.dist-info/top_level.txt
GRATIOSA-1.0.2.dist-info/RECORD
