Metadata-Version: 2.2
Name: GRATIOSA
Version: 1.0.2
Summary:  
Home-page: https://github.com/sammeyer2017/GRATIOSA.git
Author: Pineau Maïwenn, Forquet Raphaël, Meyer Sam
Author-email: sam.meyer@insa-lyon.fr
Classifier: Programming Language :: Python :: 3
Classifier: License :: OSI Approved :: GNU General Public License (GPL)
Classifier: Operating System :: OS Independent
Requires-Dist: numpy
Requires-Dist: matplotlib
Requires-Dist: pandas
Requires-Dist: pysam
Requires-Dist: scipy
Requires-Dist: statsmodels
Dynamic: author
Dynamic: author-email
Dynamic: classifier
Dynamic: description
Dynamic: home-page
Dynamic: requires-dist
Dynamic: summary
